cfbm/__init__.py
cfbm/base.py
cfbm/bm_data/.gitignore
cfbm/bm_data/__init__.py
cfbm/bm_data/get_data.py
cfbm/composite.py
cfbm/config.py
cfbm/formed.py
cfbm/primary.py
cfbm/utils.py
cfbm-2025.2.1.dist-info/METADATA
cfbm-2025.2.1.dist-info/WHEEL
cfbm-2025.2.1.dist-info/entry_points.txt
cfbm-2025.2.1.dist-info/licenses/LICENSE
cfbm-2025.2.1.dist-info/RECORD
